embodyserial/__init__.py
embodyserial/__main__.py
embodyserial/cli.py
embodyserial/embodyserial.py
embodyserial/exceptions.py
embodyserial/helpers.py
embodyserial/listeners.py
embodyserial/logging.py
embodyserial/py.typed
embody_serial-1.0.37.dist-info/METADATA
embody_serial-1.0.37.dist-info/WHEEL
embody_serial-1.0.37.dist-info/entry_points.txt
embody_serial-1.0.37.dist-info/licenses/LICENSE
embody_serial-1.0.37.dist-info/RECORD
