Metadata-Version: 2.4
Name: embody-serial
Version: 1.0.37
Summary: Communicate with the embody device over a serial port
Project-URL: Homepage, https://github.com/aidee-health/embody-serial
Project-URL: Repository, https://github.com/aidee-health/embody-serial
Project-URL: Changelog, https://github.com/aidee-health/embody-serial/releases
Author-email: Aidee Health AS <hello@aidee.io>
License-Expression: MIT
License-File: LICENSE
Classifier: Development Status :: 5 - Production/Stable
Requires-Python: <4.0,>=3.11
Requires-Dist: embody-codec>=1.0.32
Requires-Dist: pyserial>=3.5
